{
  "workgroup": "Governance Workgroup",
  "meetingDate": "2024-05-21",
  "differences": [
    {
      "field": "meetingInfo.mediaLink",
      "gitbook": "https://app.read.ai/analytics/meetings/01HYDQ846FYREVCXV6PJ7818JY?utm_source=Share_CopyLink§ion=transcript",
      "supabase": "https://app.read.ai/analytics/meetings/01HYDQ846FYREVCXV6PJ7818JY?utm_source=Share_CopyLink&section=transcript"
    },
    {
      "field": "agendaItems[0].discussionPoints[0]",
      "gitbook": "Marketing WG's Q2 budget was approved.",
      "supabase": "Marketing WG's Q2 budget was approved"
    },
    {
      "field": "agendaItems[0].discussionPoints[1]",
      "gitbook": "Discussion of objections to Writers' WG Q2 budget.",
      "supabase": "Discussion of objections to Writers' WG Q2 budget"
    },
    {
      "field": "agendaItems[0].discussionPoints[2]",
      "gitbook": "Discussion of WWG's points system and reward structure.",
      "supabase": "Discussion of WWG's points system and reward structure"
    },
    {
      "field": "agendaItems[0].discussionPoints[3]",
      "gitbook": "Discussion of error which led to omission of one of R&D Guild's project from the budget total.",
      "supabase": "Discussion of error which led to omission of one of R&D Guild's project from the budget total"
    },
    {
      "field": "agendaItems[0].decisionItems[1].effect",
      "gitbook": "affectsOnlyThisWorkgroup"
    },
    {
      "field": "noSummaryGivenText",
      "gitbook": "No Summary Given"
    },
    {
      "field": "canceledSummaryText",
      "gitbook": "Meeting was cancelled"
    }
  ]
}